djx_cmds/__init__.py
djx_cmds/admin.py
djx_cmds/apps.py
djx_cmds/format_with_jinja.py
djx_cmds/management/__init__.py
djx_cmds/management/commands/__init__.py
djx_cmds/management/commands/clean_migration.py
djx_cmds/management/commands/extract_models.py
djx_cmds/management/commands/install_app.py
djx_cmds/management/commands/models_to_angular.py
djx_cmds/management/commands/scaffolding.py
djx_cmds/management/commands/scatt.py
djx_cmds/migrations/__init__.py
djx_cmds/models.py
djx_cmds/services/__init__.py
djx_cmds/services/clean_migration.py
djx_cmds/services/extract_models_service.py
djx_cmds/services/import_object.py
djx_cmds/services/install_app_service.py
djx_cmds/services/models_to_angular_service.py
djx_cmds/services/scaffolding_service.py
djx_cmds/templates/angular.txt
djx_cmds/templates/formly.txt
djx_cmds/templates/mtx_grid_table.txt
djx_cmds/templates/serializer.txt
djx_cmds/templates/url.txt
djx_cmds/templates/view.txt
djx_cmds/tests.py
djx_cmds/views.py
djx_cmds-0.2.2.dist-info/METADATA
djx_cmds-0.2.2.dist-info/WHEEL
djx_cmds-0.2.2.dist-info/RECORD
