Metadata-Version: 2.1
Name: djx-cmds
Version: 0.2.2
Summary: 
Author: nope
Requires-Python: >=3.10,<4.0
Classifier: Programming Language :: Python :: 3
Classifier: Programming Language :: Python :: 3.10
Classifier: Programming Language :: Python :: 3.11
Requires-Dist: coreapi (>=2.3.3,<3.0.0)
Requires-Dist: django (>=4.1)
Requires-Dist: inflection (>=0.5.1,<0.6.0)
Requires-Dist: jinja2 (>=3.1.2,<4.0.0)
Requires-Dist: pyyaml (>=6.0.2,<7.0.0)
